__init__.py
missforest/__init__.py
missforest/_array.py
missforest/_info.py
missforest/_validate.py
missforest/errors.py
missforest/metrics.py
missforest/missforest.py
MissForest-4.2.3.dist-info/LICENSE
MissForest-4.2.3.dist-info/METADATA
MissForest-4.2.3.dist-info/WHEEL
MissForest-4.2.3.dist-info/top_level.txt
MissForest-4.2.3.dist-info/RECORD
