Metadata-Version: 2.1
Name: MissForest
Version: 4.2.3
Summary: Best imputation method.
Author-email: Yuen Shing Yan Hindy <yuenshingyan@gmail.com>
Project-URL: Homepage, https://github.com/yuenshingyan/MissForest
Project-URL: Bug Tracker, https://github.com/yuenshingyan/MissForest/issues
Classifier: Programming Language :: Python :: 3
Classifier: License :: OSI Approved :: MIT License
Classifier: Operating System :: OS Independent
Requires-Python: >=3.10
License-File: LICENSE
